[{"__type__":"cc.SpriteFrame","content":{"name":"pa1_2","texture":"91/GtsN/ZM6ai490Sji0Fm","rect":[1658,319,139,37],"offset":[0,0],"originalSize":[143,43],"capInsets":[0,0,0,0]}},{"__type__":"cc.SpriteFrame","content":{"name":"pa1_3","texture":"91/GtsN/ZM6ai490Sji0Fm","rect":[1109,4,338,118],"offset":[-1,1],"originalSize":[340,120],"capInsets":[0,0,0,0]}},{"__type__":"cc.SpriteFrame","content":{"name":"adw0_2","texture":"91/GtsN/ZM6ai490Sji0Fm","rect":[1103,259,103,111],"offset":[5,-8],"originalSize":[161,151],"capInsets":[0,0,0,0]}},{"__type__":"cc.SpriteFrame","content":{"name":"dw2_2_0","texture":"91/GtsN/ZM6ai490Sji0Fm","rect":[358,451,23,15],"offset":[0,0],"originalSize":[23,15],"capInsets":[0,0,0,0]}},{"__type__":"cc.SpriteFrame","content":{"name":"kre_0","texture":"91/GtsN/ZM6ai490Sji0Fm","rect":[639,188,100,64],"offset":[-9,-6],"originalSize":[140,120],"capInsets":[0,0,0,0]}},{"__type__":"cc.SpriteFrame","content":{"name":"n_1_7","texture":"91/GtsN/ZM6ai490Sji0Fm","rect":[1753,362,38,51],"offset":[0,0],"originalSize":[38,51],"capInsets":[0,0,0,0]}},{"__type__":"cc.SpriteFrame","content":{"name":"strong","texture":"91/GtsN/ZM6ai490Sji0Fm","rect":[4,4,309,309],"offset":[0,0],"originalSize":[309,309],"capInsets":[0,0,0,0]}},{"__type__":"cc.SpriteFrame","content":{"name":"k10","texture":"91/GtsN/ZM6ai490Sji0Fm","rect":[1887,349,76,49],"offset":[0,0],"originalSize":[76,49],"capInsets":[0,0,0,0]}},{"__type__":"cc.SpriteFrame","content":{"name":"fz","texture":"91/GtsN/ZM6ai490Sji0Fm","rect":[1453,90,22,23],"offset":[0,0],"originalSize":[22,23],"capInsets":[0,0,0,0]}},{"__type__":"cc.SpriteFrame","content":{"name":"n_1_5","texture":"91/GtsN/ZM6ai490Sji0Fm","rect":[1993,4,40,50],"offset":[0,0],"originalSize":[40,50],"capInsets":[0,0,0,0]}},{"__type__":"cc.SpriteFrame","content":{"name":"h3","texture":"91/GtsN/ZM6ai490Sji0Fm","rect":[358,319,112,126],"offset":[0,0],"originalSize":[112,126],"capInsets":[0,0,0,0]}},{"__type__":"cc.SpriteFrame","content":{"name":"h5","texture":"91/GtsN/ZM6ai490Sji0Fm","rect":[985,260,112,115],"offset":[0,0],"originalSize":[112,115],"capInsets":[0,0,0,0]}},{"__type__":"cc.SpriteFrame","content":{"name":"kre_2","texture":"91/GtsN/ZM6ai490Sji0Fm","rect":[1524,252,128,104],"offset":[1,4],"originalSize":[140,120],"capInsets":[0,0,0,0]}},{"__type__":"cc.SpriteFrame","content":{"name":"k12","texture":"91/GtsN/ZM6ai490Sji0Fm","rect":[1449,128,74,43],"offset":[1,0],"originalSize":[76,49],"capInsets":[0,0,0,0]}},{"__type__":"cc.SpriteFrame","content":{"name":"k17","texture":"91/GtsN/ZM6ai490Sji0Fm","rect":[1203,128,76,45],"offset":[0,1],"originalSize":[76,49],"capInsets":[0,0,0,0]}},{"__type__":"cc.SpriteFrame","content":{"name":"n_1_1","texture":"91/GtsN/ZM6ai490Sji0Fm","rect":[1899,113,17,50],"offset":[0,0],"originalSize":[17,50],"capInsets":[0,0,0,0]}},{"__type__":"cc.SpriteFrame","content":{"name":"ew1","texture":"91/GtsN/ZM6ai490Sji0Fm","rect":[1874,248,76,38],"offset":[0,0],"originalSize":[76,38],"capInsets":[0,0,0,0]}},{"__type__":"cc.SpriteFrame","content":{"name":"kl12","texture":"91/GtsN/ZM6ai490Sji0Fm","rect":[982,387,111,78],"offset":[0,2],"originalSize":[111,82],"capInsets":[0,0,0,0]}},{"__type__":"cc.SpriteFrame","content":{"name":"n_1_4","texture":"91/GtsN/ZM6ai490Sji0Fm","rect":[1922,119,42,50],"offset":[0,0],"originalSize":[42,50],"capInsets":[0,0,0,0]}},{"__type__":"cc.SpriteFrame","content":{"name":"pTail","texture":"91/GtsN/ZM6ai490Sji0Fm","rect":[304,319,48,131],"offset":[0,0],"originalSize":[48,131],"capInsets":[0,0,0,0]}},{"__type__":"cc.SpriteFrame","content":{"name":"h0","texture":"91/GtsN/ZM6ai490Sji0Fm","rect":[1216,371,86,95],"offset":[0,0],"originalSize":[86,95],"capInsets":[0,0,0,0]}},{"__type__":"cc.SpriteFrame","content":{"name":"prop_f_1","texture":"91/GtsN/ZM6ai490Sji0Fm","rect":[1830,38,135,35],"offset":[0,0],"originalSize":[135,35],"capInsets":[0,0,0,0]}},{"__type__":"cc.SpriteFrame","content":{"name":"dw2","texture":"91/GtsN/ZM6ai490Sji0Fm","rect":[1906,175,93,27],"offset":[0,0],"originalSize":[93,27],"capInsets":[0,0,0,0]}},{"__type__":"cc.SpriteFrame","content":{"name":"kl16","texture":"91/GtsN/ZM6ai490Sji0Fm","rect":[865,387,111,78],"offset":[0,2],"originalSize":[111,82],"capInsets":[0,0,0,0]}},{"__type__":"cc.SpriteFrame","content":{"name":"kl3","texture":"91/GtsN/ZM6ai490Sji0Fm","rect":[745,182,111,74],"offset":[0,-1],"originalSize":[111,82],"capInsets":[0,0,0,0]}},{"__type__":"cc.SpriteFrame","content":{"name":"k5","texture":"91/GtsN/ZM6ai490Sji0Fm","rect":[943,129,76,46],"offset":[0,0],"originalSize":[76,46],"capInsets":[0,0,0,0]}},{"__type__":"cc.SpriteFrame","content":{"name":"dw2_2_1","texture":"91/GtsN/ZM6ai490Sji0Fm","rect":[387,451,21,15],"offset":[0,0],"originalSize":[23,15],"capInsets":[0,0,0,0]}},{"__type__":"cc.SpriteFrame","content":{"name":"kl4","texture":"91/GtsN/ZM6ai490Sji0Fm","rect":[748,387,111,78],"offset":[0,2],"originalSize":[111,82],"capInsets":[0,0,0,0]}},{"__type__":"cc.SpriteFrame","content":{"name":"kl2","texture":"91/GtsN/ZM6ai490Sji0Fm","rect":[979,181,111,73],"offset":[0,0],"originalSize":[111,73],"capInsets":[0,0,0,0]}},{"__type__":"cc.SpriteFrame","content":{"name":"kl5","texture":"91/GtsN/ZM6ai490Sji0Fm","rect":[1096,180,103,73],"offset":[0,-1],"originalSize":[111,83],"capInsets":[0,0,0,0]}},{"__type__":"cc.SpriteFrame","content":{"name":"adw0_1","texture":"91/GtsN/ZM6ai490Sji0Fm","rect":[476,319,67,69],"offset":[9,-26],"originalSize":[161,151],"capInsets":[0,0,0,0]}},{"__type__":"cc.SpriteFrame","content":{"name":"hl1","texture":"91/GtsN/ZM6ai490Sji0Fm","rect":[4,319,145,145],"offset":[0,0],"originalSize":[145,145],"capInsets":[0,0,0,0]}},{"__type__":"cc.SpriteFrame","content":{"name":"n_1_2","texture":"91/GtsN/ZM6ai490Sji0Fm","rect":[1803,294,39,50],"offset":[0,0],"originalSize":[39,50],"capInsets":[0,0,0,0]}},{"__type__":"cc.SpriteFrame","content":{"name":"k9","texture":"91/GtsN/ZM6ai490Sji0Fm","rect":[1792,235,76,53],"offset":[0,0],"originalSize":[76,53],"capInsets":[0,0,0,0]}},{"__type__":"cc.SpriteFrame","content":{"name":"gold","texture":"91/GtsN/ZM6ai490Sji0Fm","rect":[1971,60,52,52],"offset":[0,0],"originalSize":[52,52],"capInsets":[0,0,0,0]}},{"__type__":"cc.SpriteFrame","content":{"name":"prop1","texture":"91/GtsN/ZM6ai490Sji0Fm","rect":[985,4,118,119],"offset":[0,0],"originalSize":[128,127],"capInsets":[0,0,0,0]}},{"__type__":"cc.SpriteFrame","content":{"name":"n_1_pt","texture":"91/GtsN/ZM6ai490Sji0Fm","rect":[304,456,9,8],"offset":[0,0],"originalSize":[33,36],"capInsets":[0,0,0,0]}},{"__type__":"cc.SpriteFrame","content":{"name":"kl1","texture":"91/GtsN/ZM6ai490Sji0Fm","rect":[1640,90,109,78],"offset":[1,1],"originalSize":[111,84],"capInsets":[0,0,0,0]}},{"__type__":"cc.SpriteFrame","content":{"name":"dw4","texture":"91/GtsN/ZM6ai490Sji0Fm","rect":[1906,208,89,34],"offset":[0,0],"originalSize":[89,34],"capInsets":[0,0,0,0]}},{"__type__":"cc.SpriteFrame","content":{"name":"adw0_3","texture":"91/GtsN/ZM6ai490Sji0Fm","rect":[1321,256,103,105],"offset":[11,-13],"originalSize":[161,151],"capInsets":[0,0,0,0]}},{"__type__":"cc.SpriteFrame","content":{"name":"prop2","texture":"91/GtsN/ZM6ai490Sji0Fm","rect":[748,262,118,119],"offset":[0,0],"originalSize":[128,127],"capInsets":[0,0,0,0]}},{"__type__":"cc.SpriteFrame","content":{"name":"font_touch","texture":"91/GtsN/ZM6ai490Sji0Fm","rect":[319,262,228,51],"offset":[0,0],"originalSize":[228,57],"capInsets":[0,0,0,0]}},{"__type__":"cc.SpriteFrame","content":{"name":"kl13","texture":"91/GtsN/ZM6ai490Sji0Fm","rect":[1314,177,103,73],"offset":[0,-1],"originalSize":[111,83],"capInsets":[0,0,0,0]}},{"__type__":"cc.SpriteFrame","content":{"name":"h2","texture":"91/GtsN/ZM6ai490Sji0Fm","rect":[1430,252,88,105],"offset":[0,0],"originalSize":[88,105],"capInsets":[0,0,0,0]}},{"__type__":"cc.SpriteFrame","content":{"name":"kre_1","texture":"91/GtsN/ZM6ai490Sji0Fm","rect":[1425,367,126,98],"offset":[0,1],"originalSize":[140,120],"capInsets":[0,0,0,0]}},{"__type__":"cc.SpriteFrame","content":{"name":"dw2_1_0","texture":"91/GtsN/ZM6ai490Sji0Fm","rect":[1786,175,32,54],"offset":[0,0],"originalSize":[32,54],"capInsets":[0,0,0,0]}},{"__type__":"cc.SpriteFrame","content":{"name":"k14","texture":"91/GtsN/ZM6ai490Sji0Fm","rect":[1825,418,76,41],"offset":[0,0],"originalSize":[76,41],"capInsets":[0,0,0,0]}},{"__type__":"cc.SpriteFrame","content":{"name":"pa1_1","texture":"91/GtsN/ZM6ai490Sji0Fm","rect":[476,394,65,33],"offset":[1,0],"originalSize":[71,37],"capInsets":[0,0,0,0]}},{"__type__":"cc.SpriteFrame","content":{"name":"n_1_9","texture":"91/GtsN/ZM6ai490Sji0Fm","rect":[1663,362,39,51],"offset":[0,0],"originalSize":[39,51],"capInsets":[0,0,0,0]}},{"__type__":"cc.SpriteFrame","content":{"name":"n_1_6","texture":"91/GtsN/ZM6ai490Sji0Fm","rect":[1708,362,39,51],"offset":[0,0],"originalSize":[39,51],"capInsets":[0,0,0,0]}},{"__type__":"cc.SpriteFrame","content":{"name":"k6","texture":"91/GtsN/ZM6ai490Sji0Fm","rect":[1907,404,76,36],"offset":[0,-1],"originalSize":[76,40],"capInsets":[0,0,0,0]}},{"__type__":"cc.SpriteFrame","content":{"name":"dw2_3_2","texture":"91/GtsN/ZM6ai490Sji0Fm","rect":[1673,174,56,61],"offset":[0,0],"originalSize":[78,83],"capInsets":[0,0,0,0]}},{"__type__":"cc.SpriteFrame","content":{"name":"kl15","texture":"91/GtsN/ZM6ai490Sji0Fm","rect":[1566,4,105,80],"offset":[-1,0],"originalSize":[109,82],"capInsets":[0,0,0,0]}},{"__type__":"cc.SpriteFrame","content":{"name":"n_1_3","texture":"91/GtsN/ZM6ai490Sji0Fm","rect":[1843,350,38,50],"offset":[0,0],"originalSize":[38,50],"capInsets":[0,0,0,0]}},{"__type__":"cc.SpriteFrame","content":{"name":"k13","texture":"91/GtsN/ZM6ai490Sji0Fm","rect":[1663,419,74,42],"offset":[1,0],"originalSize":[76,44],"capInsets":[0,0,0,0]}},{"__type__":"cc.SpriteFrame","content":{"name":"k11","texture":"91/GtsN/ZM6ai490Sji0Fm","rect":[1367,128,76,43],"offset":[0,0],"originalSize":[76,43],"capInsets":[0,0,0,0]}},{"__type__":"cc.SpriteFrame","content":{"name":"dw1","texture":"91/GtsN/ZM6ai490Sji0Fm","rect":[1930,303,76,38],"offset":[0,0],"originalSize":[76,38],"capInsets":[0,0,0,0]}},{"__type__":"cc.SpriteFrame","content":{"name":"prop_f_3","texture":"91/GtsN/ZM6ai490Sji0Fm","rect":[1830,4,157,28],"offset":[0,0],"originalSize":[157,28],"capInsets":[0,0,0,0]}},{"__type__":"cc.SpriteFrame","content":{"name":"shield1","texture":"91/GtsN/ZM6ai490Sji0Fm","rect":[577,4,100,178],"offset":[0,0],"originalSize":[100,178],"capInsets":[0,0,0,0]}},{"__type__":"cc.SpriteFrame","content":{"name":"ektail_1001","texture":"91/GtsN/ZM6ai490Sji0Fm","rect":[1423,177,129,69],"offset":[-3,-1],"originalSize":[139,75],"capInsets":[0,0,0,0]}},{"__type__":"cc.SpriteFrame","content":{"name":"effect1","texture":"91/GtsN/ZM6ai490Sji0Fm","rect":[1755,142,20,20],"offset":[0,0],"originalSize":[20,20],"capInsets":[0,0,0,0]}},{"__type__":"cc.SpriteFrame","content":{"name":"kl9","texture":"91/GtsN/ZM6ai490Sji0Fm","rect":[1453,4,107,80],"offset":[2,1],"originalSize":[111,82],"capInsets":[0,0,0,0]}},{"__type__":"cc.SpriteFrame","content":{"name":"n_1_k","texture":"91/GtsN/ZM6ai490Sji0Fm","rect":[1937,79,27,34],"offset":[0,0],"originalSize":[33,36],"capInsets":[0,0,0,0]}},{"__type__":"cc.SpriteFrame","content":{"name":"dw5_0","texture":"91/GtsN/ZM6ai490Sji0Fm","rect":[553,262,189,193],"offset":[0,0],"originalSize":[189,193],"capInsets":[0,0,0,0]}},{"__type__":"cc.SpriteFrame","content":{"name":"dw3","texture":"91/GtsN/ZM6ai490Sji0Fm","rect":[1093,129,104,45],"offset":[-1,0],"originalSize":[108,53],"capInsets":[0,0,0,0]}},{"__type__":"cc.SpriteFrame","content":{"name":"kl8","texture":"91/GtsN/ZM6ai490Sji0Fm","rect":[1099,381,111,82],"offset":[0,0],"originalSize":[111,82],"capInsets":[0,0,0,0]}},{"__type__":"cc.SpriteFrame","content":{"name":"k4","texture":"91/GtsN/ZM6ai490Sji0Fm","rect":[861,129,76,47],"offset":[0,0],"originalSize":[76,49],"capInsets":[0,0,0,0]}},{"__type__":"cc.SpriteAtlas","_name":"package_game.plist","_spriteFrames":{"adw0_0":{"__uuid__":"d50svpKEtFRZjGFo+aKH1Y"},"adw0_1":{"__uuid__":"49n0A5a8VJKoiD98k3MRis"},"adw0_2":{"__uuid__":"02ihl12tRAZYtcNWQGjyTf"},"adw0_3":{"__uuid__":"5cMxdisvpNOqPOs6gQQXKR"},"adw0_4":{"__uuid__":"ff3Ux4NrpErovH54O60XT+"},"adw0_5":{"__uuid__":"bbqf+TDPNJuKSOzbA7Qwzg"},"dw1":{"__uuid__":"7f+ouWjzRKdphjMmJ94gVK"},"dw2":{"__uuid__":"329u08YsVEKru1QTe5puJK"},"dw2_0":{"__uuid__":"c0gboNskdFZ5qQH8fV7ueq"},"dw2_1_0":{"__uuid__":"67btphk3VGoZSvt5DiADRC"},"dw2_1_1":{"__uuid__":"f6fUWuavdOBLsY8S4b+p7u"},"dw2_2_0":{"__uuid__":"050HptVxBA2JXPt/cZYXj4"},"dw2_2_1":{"__uuid__":"3e4hrFdHNEuLkbxqk12mf4"},"dw2_3_0":{"__uuid__":"a2QHRJnORMFKVSBA+Lc1ho"},"dw2_3_1":{"__uuid__":"edJMYxTPRGO7I/WoBRquqy"},"dw2_3_2":{"__uuid__":"77MnGUJZFHap/+IhsNFsM3"},"dw3":{"__uuid__":"8eQG8noaVBnYR0ceMDoBe4"},"dw4":{"__uuid__":"5arb82MVFDmIsi7HxAz3e+"},"dw5":{"__uuid__":"fbwLcXzJdB0Ymsqqvh2pat"},"dw5_0":{"__uuid__":"8d0P3+WoJI6pRnCJbDFgAx"},"effect1":{"__uuid__":"876LINdRJC9I6tiQ//1zC/"},"ektail_1001":{"__uuid__":"84ATYGfBZPA7x/T4EX6X3s"},"ew1":{"__uuid__":"28cih+G9JE97qOJixXkjNi"},"font_touch":{"__uuid__":"5e5bwlb1lJNJKtzxs4Tg6L"},"fz":{"__uuid__":"130pZrFYdB2ZMrHQROwZ42"},"gold":{"__uuid__":"534ZsOKURKo6SzHiZmcrzq"},"h0":{"__uuid__":"30CIKzzgFGFbzOk1/k3W4C"},"h1":{"__uuid__":"abaGIiM69Jhozv8ttWbURb"},"h2":{"__uuid__":"60aYoQi2FDr5PLqvWTtvFH"},"h3":{"__uuid__":"1cxrAMGE9DNbFLf84I1D91"},"h4":{"__uuid__":"dcyqWYd8hMUrEZeKTR5/1/"},"h5":{"__uuid__":"20Z2YzNWtDS71CZM9VaPqu"},"hl1":{"__uuid__":"4bRifUXadFAJ/spH34VJ+3"},"k1":{"__uuid__":"cdk7J71+5LKIrdpngJxbBs"},"k10":{"__uuid__":"118cTdnVNF6LporfFpHK1k"},"k11":{"__uuid__":"7dqNgmxuZJwp7/3sbLWSvi"},"k12":{"__uuid__":"23e7cVh3dMM4McTxkg0Y1P"},"k13":{"__uuid__":"7cor5+JmRLX4dsk7RwCnYT"},"k14":{"__uuid__":"67xonkJU1L8pKBH504G4H/"},"k15":{"__uuid__":"c1JVnoWRBHiaQOkLF9DRrd"},"k16":{"__uuid__":"f72HDmdg5LopVNo2vRKbEu"},"k17":{"__uuid__":"25vWqGsIFGapAlMpaU0iQD"},"k2":{"__uuid__":"c7SHDDT/FDLYB0NUXLvrgR"},"k3":{"__uuid__":"b8l+pqD7pAAo5eXqTcYDdP"},"k4":{"__uuid__":"95zRYFnwlHQJSAB5FWPMiM"},"k5":{"__uuid__":"39pZFH6FBLBZK6FniCpi8a"},"k6":{"__uuid__":"74FCkw/W5H0q8kXL7kZFGC"},"k7":{"__uuid__":"9dIdysCUBAaa1JxTe27x9N"},"k8":{"__uuid__":"d1G9XdGSJL0aENmuBjdruk"},"k9":{"__uuid__":"507AD4SJJBTL4L5bLre0V2"},"kl1":{"__uuid__":"58XDdM3TVH+Z4AsFsioNg2"},"kl10":{"__uuid__":"e4D68QTOBIWZ04s61b617I"},"kl11":{"__uuid__":"d8WGVclhRLdK4hOfwf9+Ow"},"kl12":{"__uuid__":"2a/cJcAllNEodZcPY3rZJ3"},"kl13":{"__uuid__":"5fSEZDo5ZC4YWv173w/pa0"},"kl14":{"__uuid__":"b2TcYb2ZxKU5ZU67+huO6D"},"kl15":{"__uuid__":"77cv5xqXlCxYGspq9Zms2O"},"kl16":{"__uuid__":"34G1b2eNZOOYyd8FzDO2rP"},"kl17":{"__uuid__":"e2/53kpkZCYoMm3p0trwjh"},"kl2":{"__uuid__":"41qpaRi9BMt4yitt7lNsV/"},"kl3":{"__uuid__":"38pKQSbqxN041FtxIK7jAC"},"kl4":{"__uuid__":"41O6ofmTJCVLk70Chyep51"},"kl5":{"__uuid__":"45TDk76+lLcoGPPf8+Nv6T"},"kl6":{"__uuid__":"ecqMBSNGNCu5SGgd4G59bT"},"kl7":{"__uuid__":"fbWN05Lv5MNaaW/ihXV7ns"},"kl8":{"__uuid__":"8fgxKyJ/9LfK9q6A0vFeGh"},"kl9":{"__uuid__":"8aJ8QM0thAHZHfgxkO4DpO"},"kre_0":{"__uuid__":"092HMFPYtGj5UXw5sAXgWD"},"kre_1":{"__uuid__":"60kMuS+jZMdK0qqtJP8XtV"},"kre_2":{"__uuid__":"22pCt9XsxFULd2nsg/aj6a"},"n_1_0":{"__uuid__":"b2UqJvOypB8aXZzcXNKcLr"},"n_1_1":{"__uuid__":"27KwFUEwBF0K8iqbXx6Ii5"},"n_1_2":{"__uuid__":"4dWminTV9ITpM2HcPcBaaA"},"n_1_3":{"__uuid__":"780dzhuWtMrrl5S/QoEBi5"},"n_1_4":{"__uuid__":"2by9KUPyNFA7bN7dNQY86E"},"n_1_5":{"__uuid__":"15JEzFOzhKpKSda9Mr1Ird"},"n_1_6":{"__uuid__":"70zhcRpTRBrbUDwP2TJlKr"},"n_1_7":{"__uuid__":"0bU5k71ptIIr3jA4wEImwL"},"n_1_8":{"__uuid__":"af4Pmk8cVNqYcU9GTJ9gDr"},"n_1_9":{"__uuid__":"6c/u5/kEpCJpLLOCgIcUmP"},"n_1_k":{"__uuid__":"8cDUytemlKaaUTTAw+IYel"},"n_1_pt":{"__uuid__":"58SykjF8JPzZspM+dPrwCo"},"n_1_sub":{"__uuid__":"e491cabDNK9rGRqdViKON2"},"p":{"__uuid__":"aaW5LbT9RHV7i7hnaXHctd"},"pTail":{"__uuid__":"2eWP1nMnhAP7FuGKsHTqaQ"},"pa1_1":{"__uuid__":"6aWedKtd1DZIuYY7q9fril"},"pa1_2":{"__uuid__":"01DbQacntNhZTLrBYGa/Nj"},"pa1_3":{"__uuid__":"02X/yQechNE79jitkNbZD8"},"prop1":{"__uuid__":"56l7UB9uRFYbj7mlukFxK4"},"prop2":{"__uuid__":"5dTdePVThIRrAIlHATPygr"},"prop3":{"__uuid__":"ffxgE4xBZAmKDkoP2LbICB"},"prop_f_1":{"__uuid__":"32Yh7eKbxDzrpQYebeziGc"},"prop_f_2":{"__uuid__":"c46A6EEORPRrBenhmvCgoJ"},"prop_f_3":{"__uuid__":"824zkOvfFP5qnWPcmd9ggk"},"r1":{"__uuid__":"9c7R7t+XFN6rpDr6bp8oa/"},"shield1":{"__uuid__":"830zKAJchC449N2fbLGo/l"},"strong":{"__uuid__":"0e3N9/9/RNXKgNwU49v9y6"},"strongDW":{"__uuid__":"f4TmnYSo9F2a0qgOT1R9dg"},"t1":{"__uuid__":"99ikJZ1blMhbsd82xIVO9d"}}},{"__type__":"cc.SpriteFrame","content":{"name":"t1","texture":"91/GtsN/ZM6ai490Sji0Fm","rect":[1025,129,62,46],"offset":[0,0],"originalSize":[62,46],"capInsets":[0,0,0,0]}},{"__type__":"cc.SpriteFrame","content":{"name":"r1","texture":"91/GtsN/ZM6ai490Sji0Fm","rect":[1989,347,37,36],"offset":[0,0],"originalSize":[37,36],"capInsets":[0,0,0,0]}},{"__type__":"cc.SpriteFrame","content":{"name":"k7","texture":"91/GtsN/ZM6ai490Sji0Fm","rect":[1848,294,76,49],"offset":[0,-2],"originalSize":[76,53],"capInsets":[0,0,0,0]}},{"__type__":"cc.SpriteFrame","content":{"name":"dw2_3_0","texture":"91/GtsN/ZM6ai490Sji0Fm","rect":[577,188,56,65],"offset":[-2,4],"originalSize":[78,83],"capInsets":[0,0,0,0]}},{"__type__":"cc.SpriteFrame","content":{"name":"p","texture":"91/GtsN/ZM6ai490Sji0Fm","rect":[1481,90,23,21],"offset":[0,0],"originalSize":[25,25],"capInsets":[0,0,0,0]}},{"__type__":"cc.SpriteFrame","content":{"name":"h1","texture":"91/GtsN/ZM6ai490Sji0Fm","rect":[872,262,107,119],"offset":[0,0],"originalSize":[107,119],"capInsets":[0,0,0,0]}},{"__type__":"cc.SpriteFrame","content":{"name":"n_1_8","texture":"91/GtsN/ZM6ai490Sji0Fm","rect":[1970,118,42,51],"offset":[0,0],"originalSize":[42,51],"capInsets":[0,0,0,0]}},{"__type__":"cc.SpriteFrame","content":{"name":"kl14","texture":"91/GtsN/ZM6ai490Sji0Fm","rect":[1677,4,109,69],"offset":[1,0],"originalSize":[111,73],"capInsets":[0,0,0,0]}},{"__type__":"cc.SpriteFrame","content":{"name":"n_1_0","texture":"91/GtsN/ZM6ai490Sji0Fm","rect":[1797,362,40,50],"offset":[0,0],"originalSize":[40,50],"capInsets":[0,0,0,0]}},{"__type__":"cc.SpriteFrame","content":{"name":"k3","texture":"91/GtsN/ZM6ai490Sji0Fm","rect":[1285,128,76,43],"offset":[0,0],"originalSize":[76,43],"capInsets":[0,0,0,0]}},{"__type__":"cc.SpriteFrame","content":{"name":"adw0_5","texture":"91/GtsN/ZM6ai490Sji0Fm","rect":[1212,258,103,107],"offset":[10,-15],"originalSize":[161,151],"capInsets":[0,0,0,0]}},{"__type__":"cc.SpriteFrame","content":{"name":"dw2_0","texture":"91/GtsN/ZM6ai490Sji0Fm","rect":[683,4,172,172],"offset":[0,0],"originalSize":[172,172],"capInsets":[0,0,0,0]}},{"__type__":"cc.SpriteFrame","content":{"name":"k15","texture":"91/GtsN/ZM6ai490Sji0Fm","rect":[1824,175,76,51],"offset":[0,0],"originalSize":[76,51],"capInsets":[0,0,0,0]}},{"__type__":"cc.SpriteFrame","content":{"name":"prop_f_2","texture":"91/GtsN/ZM6ai490Sji0Fm","rect":[1817,79,114,28],"offset":[0,0],"originalSize":[114,28],"capInsets":[0,0,0,0]}},{"__type__":"cc.SpriteFrame","content":{"name":"k2","texture":"91/GtsN/ZM6ai490Sji0Fm","rect":[1743,419,76,41],"offset":[0,0],"originalSize":[76,41],"capInsets":[0,0,0,0]}},{"__type__":"cc.SpriteFrame","content":{"name":"k1","texture":"91/GtsN/ZM6ai490Sji0Fm","rect":[476,433,65,31],"offset":[0,0],"originalSize":[65,31],"capInsets":[0,0,0,0]}},{"__type__":"cc.SpriteFrame","content":{"name":"k8","texture":"91/GtsN/ZM6ai490Sji0Fm","rect":[1817,119,76,50],"offset":[0,-1],"originalSize":[76,52],"capInsets":[0,0,0,0]}},{"__type__":"cc.SpriteFrame","content":{"name":"adw0_0","texture":"91/GtsN/ZM6ai490Sji0Fm","rect":[1735,174,45,59],"offset":[9,-33],"originalSize":[161,151],"capInsets":[0,0,0,0]}},{"__type__":"cc.SpriteFrame","content":{"name":"kl11","texture":"91/GtsN/ZM6ai490Sji0Fm","rect":[862,182,111,74],"offset":[0,-1],"originalSize":[111,82],"capInsets":[0,0,0,0]}},{"__type__":"cc.SpriteFrame","content":{"name":"h4","texture":"91/GtsN/ZM6ai490Sji0Fm","rect":[1557,362,100,98],"offset":[0,2],"originalSize":[100,102],"capInsets":[0,0,0,0]}},{"__type__":"cc.SpriteFrame","content":{"name":"kl17","texture":"91/GtsN/ZM6ai490Sji0Fm","rect":[1205,179,103,73],"offset":[1,0],"originalSize":[111,83],"capInsets":[0,0,0,0]}},{"__type__":"cc.SpriteFrame","content":{"name":"kl10","texture":"91/GtsN/ZM6ai490Sji0Fm","rect":[1308,371,111,80],"offset":[0,1],"originalSize":[111,82],"capInsets":[0,0,0,0]}},{"__type__":"cc.SpriteFrame","content":{"name":"n_1_sub","texture":"91/GtsN/ZM6ai490Sji0Fm","rect":[414,451,33,12],"offset":[0,0],"originalSize":[33,12],"capInsets":[0,0,0,0]}},{"__type__":"cc.SpriteFrame","content":{"name":"kl6","texture":"91/GtsN/ZM6ai490Sji0Fm","rect":[1558,176,109,69],"offset":[1,0],"originalSize":[111,73],"capInsets":[0,0,0,0]}},{"__type__":"cc.SpriteFrame","content":{"name":"dw2_3_1","texture":"91/GtsN/ZM6ai490Sji0Fm","rect":[1755,79,56,57],"offset":[-2,-1],"originalSize":[78,83],"capInsets":[0,0,0,0]}},{"__type__":"cc.SpriteFrame","content":{"name":"strongDW","texture":"91/GtsN/ZM6ai490Sji0Fm","rect":[319,4,252,252],"offset":[0,0],"originalSize":[252,252],"capInsets":[0,0,0,0]}},{"__type__":"cc.SpriteFrame","content":{"name":"dw2_1_1","texture":"91/GtsN/ZM6ai490Sji0Fm","rect":[1792,4,32,54],"offset":[0,0],"originalSize":[32,54],"capInsets":[0,0,0,0]}},{"__type__":"cc.SpriteFrame","content":{"name":"k16","texture":"91/GtsN/ZM6ai490Sji0Fm","rect":[1956,248,76,49],"offset":[0,0],"originalSize":[76,49],"capInsets":[0,0,0,0]}},{"__type__":"cc.SpriteFrame","content":{"name":"kl7","texture":"91/GtsN/ZM6ai490Sji0Fm","rect":[1529,90,105,80],"offset":[-1,0],"originalSize":[109,82],"capInsets":[0,0,0,0]}},{"__type__":"cc.SpriteFrame","content":{"name":"dw5","texture":"91/GtsN/ZM6ai490Sji0Fm","rect":[1658,251,128,62],"offset":[0,0],"originalSize":[128,62],"capInsets":[0,0,0,0]}},{"__type__":"cc.SpriteFrame","content":{"name":"prop3","texture":"91/GtsN/ZM6ai490Sji0Fm","rect":[861,4,118,119],"offset":[0,0],"originalSize":[128,127],"capInsets":[0,0,0,0]}},{"__type__":"cc.SpriteFrame","content":{"name":"adw0_4","texture":"91/GtsN/ZM6ai490Sji0Fm","rect":[155,319,143,145],"offset":[3,3],"originalSize":[161,151],"capInsets":[0,0,0,0]}}]