{"__type__":"cc.JsonAsset","_name":"level","json":[{"id":"1","spv":"100","sph":"80","drn":"6","reb":"3","kgd":"10","boss":"0","mpr":"10","prm":"1800","sud":"0","gbd":"1440","mas":"50","dit":"2*3#0.9*0.8","col":"3*20*60*90*120*150","bId":"1","wId":"1"},{"id":"2","spv":"100","sph":"80","drn":"6","reb":"3","kgd":"10","boss":"0","mpr":"10","prm":"1800","sud":"0","gbd":"1440","mas":"50","dit":"2*3#0.9*0.8","col":"6*12*90*150*220*250","bId":"1","wId":"1"},{"id":"3","spv":"100","sph":"80","drn":"6","reb":"3","kgd":"10","boss":"0","mpr":"10","prm":"1800","sud":"0","gbd":"1440","mas":"50","dit":"2*3#0.9*0.8","col":"7*10*85*100*220*250","bId":"1","wId":"1"},{"id":"4","spv":"100","sph":"80","drn":"6","reb":"3","kgd":"10","boss":"0","mpr":"10","prm":"1800","sud":"0","gbd":"1440","mas":"50","dit":"2*3#0.9*0.8","col":"8*39*90*250*520*550","bId":"1","wId":"1"},{"id":"5","spv":"100","sph":"80","drn":"9","reb":"3","kgd":"10","boss":"1","mpr":"10","prm":"1800","sud":"1","gbd":"1440","mas":"50","dit":"2*3#0.9*0.8","col":"20*39*90*250*520*2550","bId":"2","wId":"2"},{"id":"6","spv":"100","sph":"80","drn":"9","reb":"3","kgd":"20","boss":"0","mpr":"15","prm":"2700","sud":"0","gbd":"2160","mas":"50","dit":"2*3#0.9*0.8","col":"30*65*90*250*520*2550","bId":"2","wId":"2"},{"id":"7","spv":"100","sph":"80","drn":"9","reb":"3","kgd":"20","boss":"0","mpr":"15","prm":"2700","sud":"0","gbd":"2160","mas":"50","dit":"2*3#0.9*0.8","col":"30*65*90*250*520*2550","bId":"2","wId":"2"},{"id":"8","spv":"100","sph":"80","drn":"9","reb":"3","kgd":"20","boss":"0","mpr":"15","prm":"2700","sud":"0","gbd":"2160","mas":"50","dit":"2*3#0.9*0.8","col":"54*90*120*250*490*2550","bId":"2","wId":"2"},{"id":"9","spv":"100","sph":"80","drn":"9","reb":"3","kgd":"20","boss":"0","mpr":"15","prm":"2700","sud":"0","gbd":"2160","mas":"50","dit":"2*3#0.9*0.8","col":"54*90*120*250*490*2550","bId":"2","wId":"2"},{"id":"10","spv":"100","sph":"80","drn":"9","reb":"3","kgd":"20","boss":"1","mpr":"15","prm":"2700","sud":"2","gbd":"2160","mas":"50","dit":"2*3#0.9*0.8","col":"75*160*200*250*180*2550","bId":"3","wId":"3"},{"id":"11","spv":"100","sph":"80","drn":"9","reb":"2","kgd":"30","boss":"0","mpr":"15","prm":"3600","sud":"0","gbd":"2880","mas":"50","dit":"2*3#0.9*0.8","col":"100*160*200*250*180*2550","bId":"3","wId":"3"},{"id":"12","spv":"100","sph":"80","drn":"9","reb":"2","kgd":"30","boss":"0","mpr":"15","prm":"3600","sud":"0","gbd":"2880","mas":"50","dit":"2*3#0.9*0.8","col":"100*160*200*250*400*2550","bId":"3","wId":"3"},{"id":"13","spv":"100","sph":"80","drn":"9","reb":"2","kgd":"30","boss":"0","mpr":"15","prm":"3600","sud":"0","gbd":"2880","mas":"50","dit":"2*3#0.9*0.8","col":"100*160*200*250*400*2550","bId":"3","wId":"3"},{"id":"14","spv":"100","sph":"80","drn":"9","reb":"2","kgd":"30","boss":"0","mpr":"15","prm":"3600","sud":"0","gbd":"2880","mas":"50","dit":"2*3#0.9*0.8","col":"100*162*200*250*400*2550","bId":"3","wId":"3"},{"id":"15","spv":"100","sph":"80","drn":"9","reb":"2","kgd":"30","boss":"0","mpr":"15","prm":"3600","sud":"0","gbd":"2880","mas":"50","dit":"2*3#0.9*0.8","col":"100*200*250*390*600*2550","bId":"3","wId":"3"},{"id":"16","spv":"100","sph":"80","drn":"9","reb":"2","kgd":"40","boss":"0","mpr":"15","prm":"3600","sud":"0","gbd":"2880","mas":"50","dit":"2*3#0.9*0.8","col":"100*160*200*250*400*2550","bId":"3","wId":"3"},{"id":"17","spv":"100","sph":"80","drn":"9","reb":"2","kgd":"40","boss":"0","mpr":"15","prm":"3600","sud":"0","gbd":"2880","mas":"50","dit":"2*3#0.9*0.8","col":"100*200*250*390*600*2550","bId":"3","wId":"3"},{"id":"18","spv":"100","sph":"80","drn":"9","reb":"2","kgd":"40","boss":"0","mpr":"15","prm":"3600","sud":"0","gbd":"2880","mas":"50","dit":"2*3#0.9*0.8","col":"100*200*250*390*600*2550","bId":"3","wId":"3"},{"id":"19","spv":"100","sph":"80","drn":"9","reb":"2","kgd":"40","boss":"0","mpr":"15","prm":"3600","sud":"0","gbd":"2880","mas":"50","dit":"2*3#0.9*0.8","col":"100*200*250*390*600*2550","bId":"3","wId":"3"},{"id":"20","spv":"100","sph":"80","drn":"9","reb":"2","kgd":"40","boss":"1","mpr":"15","prm":"3600","sud":"0","gbd":"2880","mas":"50","dit":"2*3#0.9*0.8","col":"100*200*250*390*600*2550","bId":"3","wId":"3"},{"id":"21","spv":"100","sph":"80","drn":"9","reb":"2","kgd":"50","boss":"0","mpr":"20","prm":"6000","sud":"0","gbd":"4800","mas":"50","dit":"2*3#0.9*0.8","col":"100*200*250*390*600*2550","bId":"3","wId":"3"},{"id":"22","spv":"100","sph":"80","drn":"9","reb":"2","kgd":"50","boss":"0","mpr":"20","prm":"6000","sud":"0","gbd":"4800","mas":"50","dit":"2*3#0.9*0.8","col":"100*200*250*390*600*2550","bId":"3","wId":"3"},{"id":"23","spv":"100","sph":"80","drn":"9","reb":"2","kgd":"50","boss":"0","mpr":"20","prm":"6000","sud":"0","gbd":"4800","mas":"50","dit":"2*3#0.9*0.8","col":"100*200*250*390*1260*2550","bId":"3","wId":"3"},{"id":"24","spv":"100","sph":"80","drn":"9","reb":"2","kgd":"50","boss":"0","mpr":"20","prm":"6000","sud":"0","gbd":"4800","mas":"50","dit":"2*3#0.9*0.8","col":"100*200*250*390*1260*2550","bId":"3","wId":"3"},{"id":"25","spv":"100","sph":"80","drn":"9","reb":"2","kgd":"50","boss":"0","mpr":"20","prm":"6000","sud":"0","gbd":"4800","mas":"50","dit":"2*3#0.9*0.8","col":"140*280*350*546*1260*2550","bId":"3","wId":"3"},{"id":"26","spv":"100","sph":"80","drn":"9","reb":"2","kgd":"60","boss":"0","mpr":"20","prm":"6000","sud":"0","gbd":"4800","mas":"50","dit":"2*3#0.9*0.8","col":"140*280*350*546*1260*2550","bId":"3","wId":"3"},{"id":"27","spv":"100","sph":"80","drn":"9","reb":"2","kgd":"60","boss":"0","mpr":"20","prm":"6000","sud":"0","gbd":"4800","mas":"50","dit":"2*3#0.9*0.8","col":"140*280*350*546*1260*2550","bId":"3","wId":"3"},{"id":"28","spv":"100","sph":"80","drn":"9","reb":"2","kgd":"60","boss":"0","mpr":"20","prm":"6000","sud":"0","gbd":"4800","mas":"50","dit":"2*3#0.9*0.8","col":"189*315*441*882*1260*2550","bId":"3","wId":"3"},{"id":"29","spv":"100","sph":"80","drn":"9","reb":"2","kgd":"60","boss":"0","mpr":"20","prm":"6000","sud":"0","gbd":"4800","mas":"50","dit":"2*3#0.9*0.8","col":"189*315*441*882*1260*2550","bId":"3","wId":"3"},{"id":"30","spv":"100","sph":"80","drn":"9","reb":"2","kgd":"60","boss":"1","mpr":"20","prm":"6000","sud":"3","gbd":"4800","mas":"50","dit":"2*3#0.9*0.8","col":"100*200*250*390*600*2550","bId":"4","wId":"4"},{"id":"31","spv":"100","sph":"80","drn":"9","reb":"1","kgd":"60","boss":"0","mpr":"25","prm":"9000","sud":"0","gbd":"7200","mas":"50","dit":"2*3#0.9*0.8","col":"100*200*250*390*600*2550","bId":"4","wId":"4"},{"id":"32","spv":"100","sph":"80","drn":"9","reb":"1","kgd":"70","boss":"0","mpr":"25","prm":"9000","sud":"0","gbd":"7200","mas":"71","dit":"2*3#0.9*0.8","col":"100*200*250*390*600*2550","bId":"4","wId":"4"},{"id":"33","spv":"100","sph":"80","drn":"9","reb":"1","kgd":"70","boss":"0","mpr":"25","prm":"9000","sud":"0","gbd":"7200","mas":"72","dit":"2*3#0.9*0.8","col":"100*200*250*390*600*2550","bId":"4","wId":"4"},{"id":"34","spv":"100","sph":"80","drn":"9","reb":"1","kgd":"70","boss":"0","mpr":"25","prm":"9000","sud":"0","gbd":"7200","mas":"73","dit":"2*3#0.9*0.8","col":"100*200*250*390*600*2550","bId":"4","wId":"4"},{"id":"35","spv":"100","sph":"80","drn":"9","reb":"1","kgd":"70","boss":"0","mpr":"25","prm":"9000","sud":"0","gbd":"7200","mas":"74","dit":"2*3#0.9*0.8","col":"100*200*250*390*600*2550","bId":"4","wId":"4"},{"id":"36","spv":"100","sph":"80","drn":"9","reb":"1","kgd":"80","boss":"0","mpr":"25","prm":"9000","sud":"0","gbd":"7200","mas":"75","dit":"2*3#0.9*0.8","col":"120*240*300*468*720*3060","bId":"4","wId":"4"},{"id":"37","spv":"100","sph":"80","drn":"9","reb":"1","kgd":"80","boss":"0","mpr":"25","prm":"9000","sud":"0","gbd":"7200","mas":"76","dit":"2*3#0.9*0.8","col":"120*240*300*468*720*3060","bId":"4","wId":"4"},{"id":"38","spv":"100","sph":"80","drn":"9","reb":"1","kgd":"80","boss":"0","mpr":"25","prm":"9000","sud":"0","gbd":"7200","mas":"77","dit":"2*3#0.9*0.8","col":"120*240*300*468*720*3060","bId":"4","wId":"4"},{"id":"39","spv":"100","sph":"80","drn":"9","reb":"1","kgd":"80","boss":"0","mpr":"25","prm":"9000","sud":"0","gbd":"7200","mas":"78","dit":"2*3#0.9*0.8","col":"120*240*300*468*720*3060","bId":"4","wId":"4"},{"id":"40","spv":"100","sph":"80","drn":"9","reb":"1","kgd":"80","boss":"0","mpr":"25","prm":"9000","sud":"0","gbd":"7200","mas":"79","dit":"2*3#0.9*0.8","col":"144*288*360*562*864*3672","bId":"4","wId":"4"},{"id":"41","spv":"100","sph":"80","drn":"9","reb":"1","kgd":"90","boss":"0","mpr":"30","prm":"12600","sud":"0","gbd":"10080","mas":"80","dit":"2*3#0.9*0.8","col":"144*288*360*562*864*3672","bId":"4","wId":"4"},{"id":"42","spv":"100","sph":"80","drn":"9","reb":"1","kgd":"90","boss":"0","mpr":"30","prm":"12600","sud":"0","gbd":"10080","mas":"81","dit":"2*3#0.9*0.8","col":"144*288*360*562*864*3672","bId":"4","wId":"4"},{"id":"43","spv":"100","sph":"80","drn":"9","reb":"1","kgd":"90","boss":"0","mpr":"30","prm":"12600","sud":"0","gbd":"10080","mas":"82","dit":"2*3#0.9*0.8","col":"144*288*360*562*864*3672","bId":"4","wId":"4"},{"id":"44","spv":"100","sph":"80","drn":"9","reb":"1","kgd":"90","boss":"0","mpr":"30","prm":"12600","sud":"0","gbd":"10080","mas":"83","dit":"2*3#0.9*0.8","col":"144*288*360*562*864*3672","bId":"4","wId":"4"},{"id":"45","spv":"100","sph":"80","drn":"9","reb":"1","kgd":"90","boss":"0","mpr":"30","prm":"12600","sud":"0","gbd":"10080","mas":"84","dit":"2*3#0.9*0.8","col":"144*288*360*562*864*3672","bId":"4","wId":"4"},{"id":"46","spv":"100","sph":"80","drn":"9","reb":"1","kgd":"100","boss":"0","mpr":"30","prm":"12600","sud":"0","gbd":"10080","mas":"85","dit":"2*3#0.9*0.8","col":"158.4*316.8*396*618.2*950.4*4039.2","bId":"4","wId":"4"},{"id":"47","spv":"100","sph":"80","drn":"9","reb":"1","kgd":"100","boss":"0","mpr":"30","prm":"12600","sud":"0","gbd":"10080","mas":"86","dit":"2*3#0.9*0.8","col":"158.4*316.8*396*618.2*950.4*4039.2","bId":"4","wId":"4"},{"id":"48","spv":"100","sph":"80","drn":"9","reb":"1","kgd":"100","boss":"0","mpr":"30","prm":"12600","sud":"0","gbd":"10080","mas":"87","dit":"2*3#0.9*0.8","col":"174.24*348.48*435.6*680.02*1045.44*4443.12","bId":"4","wId":"4"},{"id":"49","spv":"100","sph":"80","drn":"9","reb":"1","kgd":"100","boss":"0","mpr":"30","prm":"12600","sud":"0","gbd":"10080","mas":"88","dit":"2*3#0.9*0.8","col":"174.24*348.48*435.6*680.02*1045.44*4443.12","bId":"4","wId":"4"},{"id":"50","spv":"100","sph":"80","drn":"9","reb":"1","kgd":"100","boss":"0","mpr":"30","prm":"12600","sud":"0","gbd":"10080","mas":"89","dit":"2*3#0.9*0.8","col":"100*200*250*390*600*2550","bId":"4","wId":"4"},{"id":"51","spv":"100","sph":"80","drn":"9","reb":"1","kgd":"110","boss":"0","mpr":"35","prm":"16800","sud":"0","gbd":"13440","mas":"50","dit":"2*3#0.9*0.8","col":"191.664*383.328*479.16*748.022*1149.984*4887.432","bId":"1","wId":"1"},{"id":"52","spv":"100","sph":"80","drn":"9","reb":"1","kgd":"110","boss":"0","mpr":"35","prm":"16800","sud":"0","gbd":"13440","mas":"71","dit":"2*3#0.9*0.8","col":"191.664*383.328*479.16*748.022*1149.984*4887.432","bId":"1","wId":"1"},{"id":"53","spv":"100","sph":"80","drn":"9","reb":"1","kgd":"110","boss":"0","mpr":"35","prm":"16800","sud":"0","gbd":"13440","mas":"72","dit":"2*3#0.9*0.8","col":"210.8304*421.6608*527.076*822.8242*1264.9824*5376.1752","bId":"1","wId":"1"},{"id":"54","spv":"100","sph":"80","drn":"9","reb":"1","kgd":"110","boss":"0","mpr":"35","prm":"16800","sud":"0","gbd":"13440","mas":"73","dit":"2*3#0.9*0.8","col":"210.8304*421.6608*527.076*822.8242*1264.9824*5376.1752","bId":"1","wId":"1"},{"id":"55","spv":"100","sph":"80","drn":"9","reb":"1","kgd":"110","boss":"0","mpr":"35","prm":"16800","sud":"0","gbd":"13440","mas":"74","dit":"2*3#0.9*0.8","col":"210.8304*421.6608*527.076*822.8242*1264.9824*5376.1752","bId":"1","wId":"1"},{"id":"56","spv":"100","sph":"80","drn":"9","reb":"1","kgd":"120","boss":"0","mpr":"35","prm":"16800","sud":"0","gbd":"13440","mas":"75","dit":"2*3#0.9*0.8","col":"231.91344*463.82688*579.7836*905.10662*1391.48064*5913.79272","bId":"1","wId":"1"},{"id":"57","spv":"100","sph":"80","drn":"9","reb":"1","kgd":"120","boss":"0","mpr":"35","prm":"16800","sud":"0","gbd":"13440","mas":"76","dit":"2*3#0.9*0.8","col":"231.91344*463.82688*579.7836*905.10662*1391.48064*5913.79272","bId":"1","wId":"1"},{"id":"58","spv":"100","sph":"80","drn":"9","reb":"1","kgd":"120","boss":"0","mpr":"35","prm":"16800","sud":"0","gbd":"13440","mas":"77","dit":"2*3#0.9*0.8","col":"255.104784*510.209568*637.76196*995.617282*1530.628704*6505.171992","bId":"1","wId":"1"},{"id":"59","spv":"100","sph":"80","drn":"9","reb":"1","kgd":"120","boss":"0","mpr":"35","prm":"16800","sud":"0","gbd":"13440","mas":"78","dit":"2*3#0.9*0.8","col":"255.104784*510.209568*637.76196*995.617282*1530.628704*6505.171992","bId":"1","wId":"1"},{"id":"60","spv":"100","sph":"80","drn":"9","reb":"1","kgd":"120","boss":"0","mpr":"35","prm":"9000","sud":"4","gbd":"7200","mas":"90","dit":"2*3#0.9*0.8","col":"100*200*250*390*600*2550","bId":"1","wId":"1"},{"id":"90","spv":"100","sph":"80","drn":"9","reb":"1","kgd":"100","boss":"0","mpr":"40","prm":"9000","sud":"5","gbd":"7200","mas":"90","dit":"2*3#0.9*0.8","col":"100*200*250*390*600*2550","bId":"1","wId":"1"},{"id":"101","spv":"100","sph":"80","drn":"9","reb":"1","kgd":"100","boss":"0","mpr":"50","prm":"9000","sud":"0","gbd":"7200","mas":"90","dit":"2*3#0.9*0.8","col":"100*200*250*390*600*2550","bId":"1","wId":"1"},{"id":"102","spv":"100","sph":"80","drn":"0","reb":"1","kgd":"100","boss":"0","mpr":"50","prm":"9000","sud":"0","gbd":"7200","mas":"90","dit":"2*3#0.9*0.8","col":"100*200*250*390*600*2550","bId":"4","wId":"4"},{"id":"103","spv":"100","sph":"80","drn":"0","reb":"1","kgd":"100","boss":"0","mpr":"50","prm":"9000","sud":"0","gbd":"7200","mas":"90","dit":"2*3#0.9*0.8","col":"100*200*250*390*600*2550","bId":"4","wId":"4"},{"id":"61","spv":"100","sph":"80","drn":"9","reb":"1","kgd":"30","boss":"0","mpr":"15","prm":"3600","sud":"0","gbd":"2880","mas":"50","dit":"2*3#0.9*0.8","col":"100*160*200*250*400*2550","bId":"3","wId":"3"},{"id":"62","spv":"100","sph":"80","drn":"9","reb":"1","kgd":"30","boss":"0","mpr":"15","prm":"3600","sud":"0","gbd":"2880","mas":"50","dit":"2*3#0.9*0.8","col":"100*160*200*250*400*2550","bId":"3","wId":"3"},{"id":"63","spv":"100","sph":"80","drn":"9","reb":"1","kgd":"30","boss":"0","mpr":"15","prm":"3600","sud":"0","gbd":"2880","mas":"50","dit":"2*3#0.9*0.8","col":"100*160*200*250*400*2550","bId":"3","wId":"3"},{"id":"64","spv":"100","sph":"80","drn":"9","reb":"1","kgd":"30","boss":"0","mpr":"15","prm":"3600","sud":"0","gbd":"2880","mas":"50","dit":"2*3#0.9*0.8","col":"100*160*200*250*400*2550","bId":"3","wId":"3"},{"id":"65","spv":"100","sph":"80","drn":"9","reb":"1","kgd":"30","boss":"0","mpr":"15","prm":"3600","sud":"0","gbd":"2880","mas":"50","dit":"2*3#0.9*0.8","col":"100*160*200*250*400*2550","bId":"3","wId":"3"},{"id":"66","spv":"100","sph":"80","drn":"9","reb":"1","kgd":"30","boss":"0","mpr":"15","prm":"3600","sud":"0","gbd":"2880","mas":"50","dit":"2*3#0.9*0.8","col":"100*160*200*250*400*2550","bId":"3","wId":"3"},{"id":"67","spv":"100","sph":"80","drn":"9","reb":"1","kgd":"30","boss":"0","mpr":"15","prm":"3600","sud":"0","gbd":"2880","mas":"50","dit":"2*3#0.9*0.8","col":"100*160*200*250*400*2550","bId":"3","wId":"3"},{"id":"68","spv":"100","sph":"80","drn":"9","reb":"1","kgd":"30","boss":"0","mpr":"15","prm":"3600","sud":"0","gbd":"2880","mas":"50","dit":"2*3#0.9*0.8","col":"100*160*200*250*400*2550","bId":"3","wId":"3"},{"id":"69","spv":"100","sph":"80","drn":"9","reb":"1","kgd":"30","boss":"0","mpr":"15","prm":"3600","sud":"0","gbd":"2880","mas":"50","dit":"2*3#0.9*0.8","col":"100*160*200*250*400*2550","bId":"3","wId":"3"},{"id":"70","spv":"100","sph":"80","drn":"9","reb":"1","kgd":"30","boss":"0","mpr":"15","prm":"3600","sud":"0","gbd":"2880","mas":"50","dit":"2*3#0.9*0.8","col":"100*160*200*250*400*2550","bId":"3","wId":"3"},{"id":"72","spv":"100","sph":"80","drn":"9","reb":"1","kgd":"30","boss":"0","mpr":"15","prm":"3600","sud":"0","gbd":"2880","mas":"50","dit":"2*3#0.9*0.8","col":"100*160*200*250*400*2550","bId":"3","wId":"3"},{"id":"73","spv":"100","sph":"80","drn":"9","reb":"1","kgd":"30","boss":"0","mpr":"15","prm":"3600","sud":"0","gbd":"2880","mas":"50","dit":"2*3#0.9*0.8","col":"100*160*200*250*400*2550","bId":"3","wId":"3"}]}